ctui/__init__.py
ctui/application.py
ctui/base.py
ctui/commands.py
ctui/completion.py
ctui/dialogs.py
ctui/functions.py
ctui/kaitai/velocio.ksy
ctui/keybindings.py
ctui/layout.py
ctui/style.py
ctui/types.py
ctui-0.7.9.dist-info/LICENSE
ctui-0.7.9.dist-info/METADATA
ctui-0.7.9.dist-info/WHEEL
ctui-0.7.9.dist-info/RECORD
