Metadata-Version: 2.1
Name: ctui
Version: 0.7.9
Summary: The ctui library is similar to Python's built in cmd library, but with a curses-like user interface
Home-page: https://www.controlthings.io
License: LGPL
Keywords: serial,fieldbus,ICS,control,ControlThings
Author: Justin Searle
Author-email: justin@controlthings.io
Requires-Python: >=3.8,<4.0
Classifier: Development Status :: 5 - Production/Stable
Classifier: Intended Audience :: Developers
Classifier: Intended Audience :: Information Technology
Classifier: Intended Audience :: Manufacturing
Classifier: Intended Audience :: Other Audience
Classifier: Intended Audience :: Science/Research
Classifier: License :: Other/Proprietary License
Classifier: Operating System :: Microsoft :: Windows
Classifier: Operating System :: POSIX
Classifier: Operating System :: Unix
Classifier: Programming Language :: Python :: 3
Classifier: Programming Language :: Python :: 3.8
Classifier: Programming Language :: Python :: 3.9
Classifier: Programming Language :: Python :: 3.10
Classifier: Programming Language :: Python :: 3.11
Classifier: Programming Language :: Python :: 3.12
Classifier: Topic :: Utilities
Requires-Dist: Pygments (>=2.14.0,<3.0.0)
Requires-Dist: prompt-toolkit (>=3.0.36,<4.0.0)
Requires-Dist: six (>=1.16.0,<2.0.0)
Requires-Dist: tabulate (>=0.8.0,<0.9.0)
Requires-Dist: tinydb (>=4.7.1,<5.0.0)
Project-URL: Repository, https://github.com/ControlThings-io/ctserial
